{
  "protocol_version" : "0.0.6",
  "configuration" : {
    "version" : "(6.13.0) (explicit/7ea6b90eb94)",
    "tlc" : "normal",
    "sigsgev" : "altstack",
    "notifications" : "kqueue",
    "architecture" : "amd64",
    "disabled_features" : "com,shared_perfcounters",
    "smallconfig" : "disabled",
    "bigarrays" : "disabled",
    "softdebug" : "enabled",
    "interpreter" : "enabled",
    "llvm_support" : "disabled",
    "suspend" : "preemptive"
  },
  "memory" : {
    "Resident Size" : "828477440",
    "Virtual Size" : "38928723968",
    "minor_gc_time" : "0",
    "major_gc_time" : "3199252",
    "minor_gc_count" : "0",
    "major_gc_count" : "67",
    "major_gc_time_concurrent" : "0"
 },
  "threads" : [
 {
    "is_managed" : true,
    "offset_free_hash" : "0xaa15f36dd",
    "offset_rich_hash" : "0xaa15f3867",
    "crashed" : false,
    "native_thread_id" : "0x30f431000",
    "thread_info_addr" : "0x7febe4383000",
    "thread_name" : "tid_4eab3",
    "ctx" : {
      "IP" : "0x7ff815f1b6f6",
      "SP" : "0x30f430658",
      "BP" : "0x30f4306f0"
  },
    "managed_frames" : [
  {
      "is_managed" : "false",
      "native_address" : "unregistered"
   }
,
  {
      "is_managed" : "true",
      "guid" : "E38A6D3E-E47C-43EB-9B2E-49C63FC0AA48",
      "token" : "0x00000",
      "native_offset" : "0x0",
      "filename" : "mscorlib.dll",
      "sizeofimage" : "0x470000",
      "timestamp" : "0xaf0ada7a",
      "il_offset" : "0x00000"
   }
,
  {
      "is_managed" : "true",
      "guid" : "E38A6D3E-E47C-43EB-9B2E-49C63FC0AA48",
      "token" : "0x6001f5d",
      "native_offset" : "0x0",
      "filename" : "mscorlib.dll",
      "sizeofimage" : "0x470000",
      "timestamp" : "0xaf0ada7a",
      "il_offset" : "0x0002f"
   }
,
  {
      "is_managed" : "true",
      "guid" : "E38A6D3E-E47C-43EB-9B2E-49C63FC0AA48",
      "token" : "0x6001f50",
      "native_offset" : "0x0",
      "filename" : "mscorlib.dll",
      "sizeofimage" : "0x470000",
      "timestamp" : "0xaf0ada7a",
      "il_offset" : "0x0000e"
   }
,
  {
      "is_managed" : "true",
      "guid" : "E38A6D3E-E47C-43EB-9B2E-49C63FC0AA48",
      "token" : "0x6001f52",
      "native_offset" : "0x0",
      "filename" : "mscorlib.dll",
      "sizeofimage" : "0x470000",
      "timestamp" : "0xaf0ada7a",
      "il_offset" : "0x00000"
   }
,
  {
      "is_managed" : "true",
      "guid" : "D5F9CBDF-B9F0-4FBF-95C8-63FB10686ED4",
      "token" : "0x6005777",
      "native_offset" : "0x0",
      "filename" : "unityplastic.dll",
      "sizeofimage" : "0x4c0000",
      "timestamp" : "0x6228ec27",
      "il_offset" : "0x00030"
   }
,
  {
      "is_managed" : "true",
      "guid" : "E38A6D3E-E47C-43EB-9B2E-49C63FC0AA48",
      "token" : "0x6001f7d",
      "native_offset" : "0x0",
      "filename" : "mscorlib.dll",
      "sizeofimage" : "0x470000",
      "timestamp" : "0xaf0ada7a",
      "il_offset" : "0x00014"
   }
,
  {
      "is_managed" : "true",
      "guid" : "E38A6D3E-E47C-43EB-9B2E-49C63FC0AA48",
      "token" : "0x6001f25",
      "native_offset" : "0x0",
      "filename" : "mscorlib.dll",
      "sizeofimage" : "0x470000",
      "timestamp" : "0xaf0ada7a",
      "il_offset" : "0x00071"
   }
,
  {
      "is_managed" : "true",
      "guid" : "E38A6D3E-E47C-43EB-9B2E-49C63FC0AA48",
      "token" : "0x6001f23",
      "native_offset" : "0x0",
      "filename" : "mscorlib.dll",
      "sizeofimage" : "0x470000",
      "timestamp" : "0xaf0ada7a",
      "il_offset" : "0x00000"
   }
,
  {
      "is_managed" : "true",
      "guid" : "E38A6D3E-E47C-43EB-9B2E-49C63FC0AA48",
      "token" : "0x6001f22",
      "native_offset" : "0x0",
      "filename" : "mscorlib.dll",
      "sizeofimage" : "0x470000",
      "timestamp" : "0xaf0ada7a",
      "il_offset" : "0x0002b"
   }
,
  {
      "is_managed" : "true",
      "guid" : "E38A6D3E-E47C-43EB-9B2E-49C63FC0AA48",
      "token" : "0x6001f7f",
      "native_offset" : "0x0",
      "filename" : "mscorlib.dll",
      "sizeofimage" : "0x470000",
      "timestamp" : "0xaf0ada7a",
      "il_offset" : "0x00008"
   }
,
  {
      "is_managed" : "true",
      "guid" : "E38A6D3E-E47C-43EB-9B2E-49C63FC0AA48",
      "token" : "0x00000",
      "native_offset" : "0x0",
      "filename" : "mscorlib.dll",
      "sizeofimage" : "0x470000",
      "timestamp" : "0xaf0ada7a",
      "il_offset" : "0x00065"
   }

  ],
  "unmanaged_frames" : [
 {
    "is_managed" : "false",
    "native_address" : "0x16f56851a",
    "native_offset" : "0x00000"
  }
,
 {
    "is_managed" : "false",
    "native_address" : "0x16f6c14f0",
    "native_offset" : "0x00000"
  }
,
 {
    "is_managed" : "false",
    "native_address" : "0x16f6c182a",
    "native_offset" : "0x00000"
  }
,
 {
    "is_managed" : "false",
    "native_address" : "0x16f6c15e1",
    "native_offset" : "0x00000"
  }
,
 {
    "is_managed" : "false",
    "native_address" : "0x16f5c5d71",
    "native_offset" : "0x00000"
  }
,
 {
    "is_managed" : "false",
    "native_address" : "0x7ff815f9325d",
    "native_offset" : "0x00000"
  }
,
 {
    "is_managed" : "false",
    "native_address" : "0x7ff815d65dc4",
    "native_offset" : "0x00000"
  }
,
 {
    "is_managed" : "false",
    "native_address" : "0x16f70ff4c",
    "native_offset" : "0x00000"
  }
,
 {
    "is_managed" : "false",
    "native_address" : "0x16f6cc545",
    "native_offset" : "0x00000"
  }
,
 {
    "is_managed" : "false",
    "native_address" : "0x16f6cc3a7",
    "native_offset" : "0x00000"
  }
,
 {
    "is_managed" : "false",
    "native_address" : "0x16f6fcc2c",
    "native_offset" : "0x00000"
  }
,
 {
    "is_managed" : "false",
    "native_address" : "0x16f666827",
    "native_offset" : "0x00000"
  }
,
 {
    "is_managed" : "true",
    "guid" : "E38A6D3E-E47C-43EB-9B2E-49C63FC0AA48",
    "token" : "0x00000",
    "native_offset" : "0x0",
    "filename" : "mscorlib.dll",
    "sizeofimage" : "0x470000",
    "timestamp" : "0xaf0ada7a",
    "il_offset" : "0x00000"
  }
,
 {
    "is_managed" : "true",
    "guid" : "E38A6D3E-E47C-43EB-9B2E-49C63FC0AA48",
    "token" : "0x6001f50",
    "native_offset" : "0x0",
    "filename" : "mscorlib.dll",
    "sizeofimage" : "0x470000",
    "timestamp" : "0xaf0ada7a",
    "il_offset" : "0x00000"
  }
,
 {
    "is_managed" : "true",
    "guid" : "E38A6D3E-E47C-43EB-9B2E-49C63FC0AA48",
    "token" : "0x6001f7d",
    "native_offset" : "0x0",
    "filename" : "mscorlib.dll",
    "sizeofimage" : "0x470000",
    "timestamp" : "0xaf0ada7a",
    "il_offset" : "0x00000"
  }
,
 {
    "is_managed" : "true",
    "guid" : "E38A6D3E-E47C-43EB-9B2E-49C63FC0AA48",
    "token" : "0x6001f23",
    "native_offset" : "0x0",
    "filename" : "mscorlib.dll",
    "sizeofimage" : "0x470000",
    "timestamp" : "0xaf0ada7a",
    "il_offset" : "0x00000"
  }
,
 {
    "is_managed" : "false",
    "native_address" : "0x16f4ebf3c",
    "native_offset" : "0x00000"
  }
,
 {
    "is_managed" : "false",
    "native_address" : "0x16f6a1467",
    "native_offset" : "0x00000"
  }
,
 {
    "is_managed" : "false",
    "native_address" : "0x16f6a2f71",
    "native_offset" : "0x00000"
  }
,
 {
    "is_managed" : "false",
    "native_address" : "0x16f6c230c",
    "native_offset" : "0x00000"
  }
,
 {
    "is_managed" : "false",
    "native_address" : "0x16f6c20dd",
    "native_offset" : "0x00000"
  }
,
 {
    "is_managed" : "false",
    "native_address" : "0x16f73f381",
    "native_offset" : "0x00000"
  }
,
 {
    "is_managed" : "false",
    "native_address" : "0x16f73f319",
    "native_offset" : "0x00000"
  }
,
 {
    "is_managed" : "false",
    "native_address" : "0x7ff815f5adf1",
    "native_offset" : "0x00000"
  }
,
 {
    "is_managed" : "false",
    "native_address" : "0x7ff815f56857",
    "native_offset" : "0x00000"
  }

 ]
},
{
  "is_managed" : false,
  "offset_free_hash" : "0x0",
  "offset_rich_hash" : "0x0",
  "crashed" : true,
  "native_thread_id" : "0x206dfc200",
  "thread_info_addr" : "0x7feb95a3ac00",
  "thread_name" : "tid_103",
  "ctx" : {
    "IP" : "0x7ff8161a04de",
    "SP" : "0x30b8428c0",
    "BP" : "0x30b8429f0"
 },
  "unmanaged_frames" : [
 {
    "is_managed" : "false",
    "native_address" : "0x16f56851a",
    "native_offset" : "0x00000"
  }
,
 {
    "is_managed" : "false",
    "native_address" : "0x16f6c14f0",
    "native_offset" : "0x00000"
  }
,
 {
    "is_managed" : "false",
    "native_address" : "0x16f6c182a",
    "native_offset" : "0x00000"
  }
,
 {
    "is_managed" : "false",
    "native_address" : "0x16f6c1ddf",
    "native_offset" : "0x00000"
  }
,
 {
    "is_managed" : "false",
    "native_address" : "0x16f5c6ab9",
    "native_offset" : "0x00000"
  }
,
 {
    "is_managed" : "false",
    "native_address" : "0x16f56cab7",
    "native_offset" : "0x00000"
  }
,
 {
    "is_managed" : "false",
    "native_address" : "0x16f4e8d50",
    "native_offset" : "0x00000"
  }
,
 {
    "is_managed" : "false",
    "native_address" : "0x7ff815f9325d",
    "native_offset" : "0x00000"
  }
,
 {
    "is_managed" : "false",
    "native_address" : "0x1190a9f00",
    "native_offset" : "0x00000"
  }
,
 {
    "is_managed" : "false",
    "native_address" : "0x7ff81606e18f",
    "native_offset" : "0x00000"
  }
,
 {
    "is_managed" : "false",
    "native_address" : "0x7ff8198e0209",
    "native_offset" : "0x00000"
  }
,
 {
    "is_managed" : "false",
    "native_address" : "0x7ff8198a6e70",
    "native_offset" : "0x00000"
  }
,
 {
    "is_managed" : "false",
    "native_address" : "0x7ff81606e01a",
    "native_offset" : "0x00000"
  }
,
 {
    "is_managed" : "false",
    "native_address" : "0x7ff816043b24",
    "native_offset" : "0x00000"
  }
,
 {
    "is_managed" : "false",
    "native_address" : "0x7ff816043a65",
    "native_offset" : "0x00000"
  }
,
 {
    "is_managed" : "false",
    "native_address" : "0x7ff8160426d7",
    "native_offset" : "0x00000"
  }
,
 {
    "is_managed" : "false",
    "native_address" : "0x7ff8160415d0",
    "native_offset" : "0x00000"
  }
,
 {
    "is_managed" : "false",
    "native_address" : "0x7ff821f380d4",
    "native_offset" : "0x00000"
  }
,
 {
    "is_managed" : "false",
    "native_address" : "0x7ff821f3af97",
    "native_offset" : "0x00000"
  }
,
 {
    "is_managed" : "false",
    "native_address" : "0x7ff8220c419a",
    "native_offset" : "0x00000"
  }
,
 {
    "is_managed" : "false",
    "native_address" : "0x7ff819a12e2d",
    "native_offset" : "0x00000"
  }
,
 {
    "is_managed" : "false",
    "native_address" : "0x7ff81a4a0d27",
    "native_offset" : "0x00000"
  }
,
 {
    "is_managed" : "false",
    "native_address" : "0x7ff819a03f19",
    "native_offset" : "0x00000"
  }
,
 {
    "is_managed" : "false",
    "native_address" : "0x7ff8199d7085",
    "native_offset" : "0x00000"
  }
,
 {
    "is_managed" : "false",
    "native_address" : "0x10352f915",
    "native_offset" : "0x00000"
  }
,
 {
    "is_managed" : "false",
    "native_address" : "0x10352fc39",
    "native_offset" : "0x00000"
  }
,
 {
    "is_managed" : "false",
    "native_address" : "0x206d3d530",
    "native_offset" : "0x00000"
  }

 ]
},
{
  "is_managed" : true,
  "offset_free_hash" : "0xbda722ad3",
  "offset_rich_hash" : "0xbda722c9d",
  "crashed" : false,
  "native_thread_id" : "0x30f22e000",
  "thread_info_addr" : "0x7febe4510000",
  "thread_name" : "Timer-Scheduler",
  "ctx" : {
    "IP" : "0x7ff815f1b6f6",
    "SP" : "0x30f22d068",
    "BP" : "0x30f22d100"
 },
  "managed_frames" : [
 {
    "is_managed" : "false",
    "native_address" : "unregistered"
  }
,
 {
    "is_managed" : "true",
    "guid" : "E38A6D3E-E47C-43EB-9B2E-49C63FC0AA48",
    "token" : "0x00000",
    "native_offset" : "0x0",
    "filename" : "mscorlib.dll",
    "sizeofimage" : "0x470000",
    "timestamp" : "0xaf0ada7a",
    "il_offset" : "0x00000"
  }
,
 {
    "is_managed" : "true",
    "guid" : "E38A6D3E-E47C-43EB-9B2E-49C63FC0AA48",
    "token" : "0x60020b2",
    "native_offset" : "0x0",
    "filename" : "mscorlib.dll",
    "sizeofimage" : "0x470000",
    "timestamp" : "0xaf0ada7a",
    "il_offset" : "0x00044"
  }
,
 {
    "is_managed" : "true",
    "guid" : "E38A6D3E-E47C-43EB-9B2E-49C63FC0AA48",
    "token" : "0x600209e",
    "native_offset" : "0x0",
    "filename" : "mscorlib.dll",
    "sizeofimage" : "0x470000",
    "timestamp" : "0xaf0ada7a",
    "il_offset" : "0x00014"
  }
,
 {
    "is_managed" : "true",
    "guid" : "E38A6D3E-E47C-43EB-9B2E-49C63FC0AA48",
    "token" : "0x600209d",
    "native_offset" : "0x0",
    "filename" : "mscorlib.dll",
    "sizeofimage" : "0x470000",
    "timestamp" : "0xaf0ada7a",
    "il_offset" : "0x00000"
  }
,
 {
    "is_managed" : "true",
    "guid" : "E38A6D3E-E47C-43EB-9B2E-49C63FC0AA48",
    "token" : "0x6002098",
    "native_offset" : "0x0",
    "filename" : "mscorlib.dll",
    "sizeofimage" : "0x470000",
    "timestamp" : "0xaf0ada7a",
    "il_offset" : "0x00019"
  }
,
 {
    "is_managed" : "true",
    "guid" : "E38A6D3E-E47C-43EB-9B2E-49C63FC0AA48",
    "token" : "0x600209b",
    "native_offset" : "0x0",
    "filename" : "mscorlib.dll",
    "sizeofimage" : "0x470000",
    "timestamp" : "0xaf0ada7a",
    "il_offset" : "0x00000"
  }
,
 {
    "is_managed" : "true",
    "guid" : "E38A6D3E-E47C-43EB-9B2E-49C63FC0AA48",
    "token" : "0x600215a",
    "native_offset" : "0x0",
    "filename" : "mscorlib.dll",
    "sizeofimage" : "0x470000",
    "timestamp" : "0xaf0ada7a",
    "il_offset" : "0x0003c"
  }
,
 {
    "is_managed" : "true",
    "guid" : "E38A6D3E-E47C-43EB-9B2E-49C63FC0AA48",
    "token" : "0x6001f7d",
    "native_offset" : "0x0",
    "filename" : "mscorlib.dll",
    "sizeofimage" : "0x470000",
    "timestamp" : "0xaf0ada7a",
    "il_offset" : "0x00014"
  }
,
 {
    "is_managed" : "true",
    "guid" : "E38A6D3E-E47C-43EB-9B2E-49C63FC0AA48",
    "token" : "0x6001f25",
    "native_offset" : "0x0",
    "filename" : "mscorlib.dll",
    "sizeofimage" : "0x470000",
    "timestamp" : "0xaf0ada7a",
    "il_offset" : "0x00071"
  }
,
 {
    "is_managed" : "true",
    "guid" : "E38A6D3E-E47C-43EB-9B2E-49C63FC0AA48",
    "token" : "0x6001f23",
    "native_offset" : "0x0",
    "filename" : "mscorlib.dll",
    "sizeofimage" : "0x470000",
    "timestamp" : "0xaf0ada7a",
    "il_offset" : "0x00000"
  }
,
 {
    "is_managed" : "true",
    "guid" : "E38A6D3E-E47C-43EB-9B2E-49C63FC0AA48",
    "token" : "0x6001f22",
    "native_offset" : "0x0",
    "filename" : "mscorlib.dll",
    "sizeofimage" : "0x470000",
    "timestamp" : "0xaf0ada7a",
    "il_offset" : "0x0002b"
  }
,
 {
    "is_managed" : "true",
    "guid" : "E38A6D3E-E47C-43EB-9B2E-49C63FC0AA48",
    "token" : "0x6001f7f",
    "native_offset" : "0x0",
    "filename" : "mscorlib.dll",
    "sizeofimage" : "0x470000",
    "timestamp" : "0xaf0ada7a",
    "il_offset" : "0x00008"
  }
,
 {
    "is_managed" : "true",
    "guid" : "E38A6D3E-E47C-43EB-9B2E-49C63FC0AA48",
    "token" : "0x00000",
    "native_offset" : "0x0",
    "filename" : "mscorlib.dll",
    "sizeofimage" : "0x470000",
    "timestamp" : "0xaf0ada7a",
    "il_offset" : "0x00065"
  }

 ],
"unmanaged_frames" : [
{
  "is_managed" : "false",
  "native_address" : "0x16f56851a",
  "native_offset" : "0x00000"
 }
,
{
  "is_managed" : "false",
  "native_address" : "0x16f6c14f0",
  "native_offset" : "0x00000"
 }
,
{
  "is_managed" : "false",
  "native_address" : "0x16f6c182a",
  "native_offset" : "0x00000"
 }
,
{
  "is_managed" : "false",
  "native_address" : "0x16f6c15e1",
  "native_offset" : "0x00000"
 }
,
{
  "is_managed" : "false",
  "native_address" : "0x16f5c5d71",
  "native_offset" : "0x00000"
 }
,
{
  "is_managed" : "false",
  "native_address" : "0x7ff815f9325d",
  "native_offset" : "0x00000"
 }
,
{
  "is_managed" : "false",
  "native_address" : "unregistered"
 }
,
{
  "is_managed" : "false",
  "native_address" : "0x16f70ff4c",
  "native_offset" : "0x00000"
 }
,
{
  "is_managed" : "false",
  "native_address" : "0x16f6cc545",
  "native_offset" : "0x00000"
 }
,
{
  "is_managed" : "false",
  "native_address" : "0x16f6cc3a7",
  "native_offset" : "0x00000"
 }
,
{
  "is_managed" : "false",
  "native_address" : "0x16f6cc63c",
  "native_offset" : "0x00000"
 }
,
{
  "is_managed" : "false",
  "native_address" : "0x16f6bcd12",
  "native_offset" : "0x00000"
 }
,
{
  "is_managed" : "false",
  "native_address" : "0x16f667f5e",
  "native_offset" : "0x00000"
 }
,
{
  "is_managed" : "true",
  "guid" : "E38A6D3E-E47C-43EB-9B2E-49C63FC0AA48",
  "token" : "0x00000",
  "native_offset" : "0x0",
  "filename" : "mscorlib.dll",
  "sizeofimage" : "0x470000",
  "timestamp" : "0xaf0ada7a",
  "il_offset" : "0x00000"
 }
,
{
  "is_managed" : "true",
  "guid" : "E38A6D3E-E47C-43EB-9B2E-49C63FC0AA48",
  "token" : "0x600209e",
  "native_offset" : "0x0",
  "filename" : "mscorlib.dll",
  "sizeofimage" : "0x470000",
  "timestamp" : "0xaf0ada7a",
  "il_offset" : "0x00000"
 }
,
{
  "is_managed" : "true",
  "guid" : "E38A6D3E-E47C-43EB-9B2E-49C63FC0AA48",
  "token" : "0x6001f7d",
  "native_offset" : "0x0",
  "filename" : "mscorlib.dll",
  "sizeofimage" : "0x470000",
  "timestamp" : "0xaf0ada7a",
  "il_offset" : "0x00000"
 }
,
{
  "is_managed" : "true",
  "guid" : "E38A6D3E-E47C-43EB-9B2E-49C63FC0AA48",
  "token" : "0x6001f23",
  "native_offset" : "0x0",
  "filename" : "mscorlib.dll",
  "sizeofimage" : "0x470000",
  "timestamp" : "0xaf0ada7a",
  "il_offset" : "0x00000"
 }
,
{
  "is_managed" : "false",
  "native_address" : "0x16f4ebf3c",
  "native_offset" : "0x00000"
 }
,
{
  "is_managed" : "false",
  "native_address" : "0x16f6a1467",
  "native_offset" : "0x00000"
 }
,
{
  "is_managed" : "false",
  "native_address" : "0x16f6a2f71",
  "native_offset" : "0x00000"
 }
,
{
  "is_managed" : "false",
  "native_address" : "0x16f6c230c",
  "native_offset" : "0x00000"
 }
,
{
  "is_managed" : "false",
  "native_address" : "0x16f6c20dd",
  "native_offset" : "0x00000"
 }
,
{
  "is_managed" : "false",
  "native_address" : "0x16f73f381",
  "native_offset" : "0x00000"
 }
,
{
  "is_managed" : "false",
  "native_address" : "0x16f73f319",
  "native_offset" : "0x00000"
 }
,
{
  "is_managed" : "false",
  "native_address" : "0x7ff815f5adf1",
  "native_offset" : "0x00000"
 }
,
{
  "is_managed" : "false",
  "native_address" : "0x7ff815f56857",
  "native_offset" : "0x00000"
 }

]
},
{
"is_managed" : false,
"offset_free_hash" : "0x0",
"offset_rich_hash" : "0x0",
"crashed" : false,
"native_thread_id" : "0x30d6a3000",
"thread_info_addr" : "0x7febc232e600",
"thread_name" : "tid_7b52f",
"ctx" : {
  "IP" : "0x7ff815f18ac6",
  "SP" : "0x30d6a2d58",
  "BP" : "0x30d6a2d70"
},
"unmanaged_frames" : [
{
  "is_managed" : "false",
  "native_address" : "0x16f56851a",
  "native_offset" : "0x00000"
 }
,
{
  "is_managed" : "false",
  "native_address" : "0x16f6c14f0",
  "native_offset" : "0x00000"
 }
,
{
  "is_managed" : "false",
  "native_address" : "0x16f6c182a",
  "native_offset" : "0x00000"
 }
,
{
  "is_managed" : "false",
  "native_address" : "0x16f6c15e1",
  "native_offset" : "0x00000"
 }
,
{
  "is_managed" : "false",
  "native_address" : "0x16f5c5d71",
  "native_offset" : "0x00000"
 }
,
{
  "is_managed" : "false",
  "native_address" : "0x7ff815f9325d",
  "native_offset" : "0x00000"
 }
,
{
  "is_managed" : "false",
  "native_address" : "0x16f71cee8",
  "native_offset" : "0x00000"
 }
,
{
  "is_managed" : "false",
  "native_address" : "0x7ff815db10c6",
  "native_offset" : "0x00000"
 }
,
{
  "is_managed" : "false",
  "native_address" : "0x1036ffbd8",
  "native_offset" : "0x00000"
 }
,
{
  "is_managed" : "false",
  "native_address" : "0x100f0677a",
  "native_offset" : "0x00000"
 }
,
{
  "is_managed" : "false",
  "native_address" : "0x10130b594",
  "native_offset" : "0x00000"
 }
,
{
  "is_managed" : "false",
  "native_address" : "0x10130b135",
  "native_offset" : "0x00000"
 }
,
{
  "is_managed" : "false",
  "native_address" : "0x10130b098",
  "native_offset" : "0x00000"
 }
,
{
  "is_managed" : "false",
  "native_address" : "0x1014a667b",
  "native_offset" : "0x00000"
 }
,
{
  "is_managed" : "false",
  "native_address" : "0x7ff815f5adf1",
  "native_offset" : "0x00000"
 }
,
{
  "is_managed" : "false",
  "native_address" : "0x7ff815f56857",
  "native_offset" : "0x00000"
 }

]
},
{
"is_managed" : false,
"offset_free_hash" : "0x0",
"offset_rich_hash" : "0x0",
"crashed" : false,
"native_thread_id" : "0x30fa3a000",
"thread_info_addr" : "0x7feb97ed9600",
"thread_name" : "Thread Pool I/O Selector",
"ctx" : {
  "IP" : "0x7ff815f219fe",
  "SP" : "0x30fa39b78",
  "BP" : "0x30fa39d50"
},
"unmanaged_frames" : [
{
  "is_managed" : "false",
  "native_address" : "0x16f56851a",
  "native_offset" : "0x00000"
 }
,
{
  "is_managed" : "false",
  "native_address" : "0x16f6c14f0",
  "native_offset" : "0x00000"
 }
,
{
  "is_managed" : "false",
  "native_address" : "0x16f6c182a",
  "native_offset" : "0x00000"
 }
,
{
  "is_managed" : "false",
  "native_address" : "0x16f6c15e1",
  "native_offset" : "0x00000"
 }
,
{
  "is_managed" : "false",
  "native_address" : "0x16f5c5d71",
  "native_offset" : "0x00000"
 }
,
{
  "is_managed" : "false",
  "native_address" : "0x7ff815f9325d",
  "native_offset" : "0x00000"
 }
,
{
  "is_managed" : "false",
  "native_address" : "unregistered"
 }
,
{
  "is_managed" : "false",
  "native_address" : "0x16f6c6404",
  "native_offset" : "0x00000"
 }
,
{
  "is_managed" : "false",
  "native_address" : "0x16f6c5e8d",
  "native_offset" : "0x00000"
 }
,
{
  "is_managed" : "false",
  "native_address" : "0x16f6c2238",
  "native_offset" : "0x00000"
 }
,
{
  "is_managed" : "false",
  "native_address" : "0x16f6c20dd",
  "native_offset" : "0x00000"
 }
,
{
  "is_managed" : "false",
  "native_address" : "0x16f73f381",
  "native_offset" : "0x00000"
 }
,
{
  "is_managed" : "false",
  "native_address" : "0x16f73f319",
  "native_offset" : "0x00000"
 }
,
{
  "is_managed" : "false",
  "native_address" : "0x7ff815f5adf1",
  "native_offset" : "0x00000"
 }
,
{
  "is_managed" : "false",
  "native_address" : "0x7ff815f56857",
  "native_offset" : "0x00000"
 }

]
},
{
"is_managed" : false,
"offset_free_hash" : "0x0",
"offset_rich_hash" : "0x0",
"crashed" : false,
"native_thread_id" : "0x30df87000",
"thread_info_addr" : "0x7feb95a7b200",
"thread_name" : "Debugger agent",
"ctx" : {
  "IP" : "0x7ff815f1f8da",
  "SP" : "0x30df86ae8",
  "BP" : "0x30df86b20"
},
"unmanaged_frames" : [
{
  "is_managed" : "false",
  "native_address" : "0x16f56851a",
  "native_offset" : "0x00000"
 }
,
{
  "is_managed" : "false",
  "native_address" : "0x16f6c14f0",
  "native_offset" : "0x00000"
 }
,
{
  "is_managed" : "false",
  "native_address" : "0x16f6c182a",
  "native_offset" : "0x00000"
 }
,
{
  "is_managed" : "false",
  "native_address" : "0x16f6c15e1",
  "native_offset" : "0x00000"
 }
,
{
  "is_managed" : "false",
  "native_address" : "0x16f5c5d71",
  "native_offset" : "0x00000"
 }
,
{
  "is_managed" : "false",
  "native_address" : "0x7ff815f9325d",
  "native_offset" : "0x00000"
 }
,
{
  "is_managed" : "false",
  "native_address" : "unregistered"
 }
,
{
  "is_managed" : "false",
  "native_address" : "0x16f5f6c59",
  "native_offset" : "0x00000"
 }
,
{
  "is_managed" : "false",
  "native_address" : "0x16f6c2238",
  "native_offset" : "0x00000"
 }
,
{
  "is_managed" : "false",
  "native_address" : "0x16f6c20dd",
  "native_offset" : "0x00000"
 }
,
{
  "is_managed" : "false",
  "native_address" : "0x16f73f381",
  "native_offset" : "0x00000"
 }
,
{
  "is_managed" : "false",
  "native_address" : "0x16f73f319",
  "native_offset" : "0x00000"
 }
,
{
  "is_managed" : "false",
  "native_address" : "0x7ff815f5adf1",
  "native_offset" : "0x00000"
 }
,
{
  "is_managed" : "false",
  "native_address" : "0x7ff815f56857",
  "native_offset" : "0x00000"
 }

]
},
{
"is_managed" : true,
"offset_free_hash" : "0xc648e2f1d",
"offset_rich_hash" : "0xc648e30ca",
"crashed" : false,
"native_thread_id" : "0x30f837000",
"thread_info_addr" : "0x7febc1adc200",
"thread_name" : "tid_5bf03",
"ctx" : {
  "IP" : "0x7ff815f1b6f6",
  "SP" : "0x30f8365c8",
  "BP" : "0x30f836660"
},
"managed_frames" : [
{
  "is_managed" : "false",
  "native_address" : "unregistered"
 }
,
{
  "is_managed" : "true",
  "guid" : "E38A6D3E-E47C-43EB-9B2E-49C63FC0AA48",
  "token" : "0x00000",
  "native_offset" : "0x0",
  "filename" : "mscorlib.dll",
  "sizeofimage" : "0x470000",
  "timestamp" : "0xaf0ada7a",
  "il_offset" : "0x00000"
 }
,
{
  "is_managed" : "true",
  "guid" : "E38A6D3E-E47C-43EB-9B2E-49C63FC0AA48",
  "token" : "0x6001f5d",
  "native_offset" : "0x0",
  "filename" : "mscorlib.dll",
  "sizeofimage" : "0x470000",
  "timestamp" : "0xaf0ada7a",
  "il_offset" : "0x0002f"
 }
,
{
  "is_managed" : "true",
  "guid" : "E38A6D3E-E47C-43EB-9B2E-49C63FC0AA48",
  "token" : "0x6001f50",
  "native_offset" : "0x0",
  "filename" : "mscorlib.dll",
  "sizeofimage" : "0x470000",
  "timestamp" : "0xaf0ada7a",
  "il_offset" : "0x0000e"
 }
,
{
  "is_managed" : "true",
  "guid" : "E38A6D3E-E47C-43EB-9B2E-49C63FC0AA48",
  "token" : "0x6001f52",
  "native_offset" : "0x0",
  "filename" : "mscorlib.dll",
  "sizeofimage" : "0x470000",
  "timestamp" : "0xaf0ada7a",
  "il_offset" : "0x00000"
 }
,
{
  "is_managed" : "true",
  "guid" : "D5F9CBDF-B9F0-4FBF-95C8-63FB10686ED4",
  "token" : "0x6001437",
  "native_offset" : "0x0",
  "filename" : "unityplastic.dll",
  "sizeofimage" : "0x4c0000",
  "timestamp" : "0x6228ec27",
  "il_offset" : "0x00014"
 }
,
{
  "is_managed" : "true",
  "guid" : "D5F9CBDF-B9F0-4FBF-95C8-63FB10686ED4",
  "token" : "0x6001435",
  "native_offset" : "0x0",
  "filename" : "unityplastic.dll",
  "sizeofimage" : "0x4c0000",
  "timestamp" : "0x6228ec27",
  "il_offset" : "0x0003f"
 }
,
{
  "is_managed" : "true",
  "guid" : "E38A6D3E-E47C-43EB-9B2E-49C63FC0AA48",
  "token" : "0x6001f7d",
  "native_offset" : "0x0",
  "filename" : "mscorlib.dll",
  "sizeofimage" : "0x470000",
  "timestamp" : "0xaf0ada7a",
  "il_offset" : "0x00014"
 }
,
{
  "is_managed" : "true",
  "guid" : "E38A6D3E-E47C-43EB-9B2E-49C63FC0AA48",
  "token" : "0x6001f25",
  "native_offset" : "0x0",
  "filename" : "mscorlib.dll",
  "sizeofimage" : "0x470000",
  "timestamp" : "0xaf0ada7a",
  "il_offset" : "0x00071"
 }
,
{
  "is_managed" : "true",
  "guid" : "E38A6D3E-E47C-43EB-9B2E-49C63FC0AA48",
  "token" : "0x6001f23",
  "native_offset" : "0x0",
  "filename" : "mscorlib.dll",
  "sizeofimage" : "0x470000",
  "timestamp" : "0xaf0ada7a",
  "il_offset" : "0x00000"
 }
,
{
  "is_managed" : "true",
  "guid" : "E38A6D3E-E47C-43EB-9B2E-49C63FC0AA48",
  "token" : "0x6001f22",
  "native_offset" : "0x0",
  "filename" : "mscorlib.dll",
  "sizeofimage" : "0x470000",
  "timestamp" : "0xaf0ada7a",
  "il_offset" : "0x0002b"
 }
,
{
  "is_managed" : "true",
  "guid" : "E38A6D3E-E47C-43EB-9B2E-49C63FC0AA48",
  "token" : "0x6001f7f",
  "native_offset" : "0x0",
  "filename" : "mscorlib.dll",
  "sizeofimage" : "0x470000",
  "timestamp" : "0xaf0ada7a",
  "il_offset" : "0x00008"
 }
,
{
  "is_managed" : "true",
  "guid" : "E38A6D3E-E47C-43EB-9B2E-49C63FC0AA48",
  "token" : "0x00000",
  "native_offset" : "0x0",
  "filename" : "mscorlib.dll",
  "sizeofimage" : "0x470000",
  "timestamp" : "0xaf0ada7a",
  "il_offset" : "0x00065"
 }

],
"unmanaged_frames" : [
{
"is_managed" : "false",
"native_address" : "0x16f56851a",
"native_offset" : "0x00000"
}
,
{
"is_managed" : "false",
"native_address" : "0x16f6c14f0",
"native_offset" : "0x00000"
}
,
{
"is_managed" : "false",
"native_address" : "0x16f6c182a",
"native_offset" : "0x00000"
}
,
{
"is_managed" : "false",
"native_address" : "0x16f6c15e1",
"native_offset" : "0x00000"
}
,
{
"is_managed" : "false",
"native_address" : "0x16f5c5d71",
"native_offset" : "0x00000"
}
,
{
"is_managed" : "false",
"native_address" : "0x7ff815f9325d",
"native_offset" : "0x00000"
}
,
{
"is_managed" : "false",
"native_address" : "unregistered"
}
,
{
"is_managed" : "false",
"native_address" : "0x16f70ff4c",
"native_offset" : "0x00000"
}
,
{
"is_managed" : "false",
"native_address" : "0x16f6cc545",
"native_offset" : "0x00000"
}
,
{
"is_managed" : "false",
"native_address" : "0x16f6cc3a7",
"native_offset" : "0x00000"
}
,
{
"is_managed" : "false",
"native_address" : "0x16f6fcc2c",
"native_offset" : "0x00000"
}
,
{
"is_managed" : "false",
"native_address" : "0x16f666827",
"native_offset" : "0x00000"
}
,
{
"is_managed" : "true",
"guid" : "E38A6D3E-E47C-43EB-9B2E-49C63FC0AA48",
"token" : "0x00000",
"native_offset" : "0x0",
"filename" : "mscorlib.dll",
"sizeofimage" : "0x470000",
"timestamp" : "0xaf0ada7a",
"il_offset" : "0x00000"
}
,
{
"is_managed" : "true",
"guid" : "E38A6D3E-E47C-43EB-9B2E-49C63FC0AA48",
"token" : "0x6001f50",
"native_offset" : "0x0",
"filename" : "mscorlib.dll",
"sizeofimage" : "0x470000",
"timestamp" : "0xaf0ada7a",
"il_offset" : "0x00000"
}
,
{
"is_managed" : "true",
"guid" : "D5F9CBDF-B9F0-4FBF-95C8-63FB10686ED4",
"token" : "0x6001435",
"native_offset" : "0x0",
"filename" : "unityplastic.dll",
"sizeofimage" : "0x4c0000",
"timestamp" : "0x6228ec27",
"il_offset" : "0x00000"
}
,
{
"is_managed" : "true",
"guid" : "E38A6D3E-E47C-43EB-9B2E-49C63FC0AA48",
"token" : "0x6001f7d",
"native_offset" : "0x0",
"filename" : "mscorlib.dll",
"sizeofimage" : "0x470000",
"timestamp" : "0xaf0ada7a",
"il_offset" : "0x00000"
}
,
{
"is_managed" : "true",
"guid" : "E38A6D3E-E47C-43EB-9B2E-49C63FC0AA48",
"token" : "0x6001f23",
"native_offset" : "0x0",
"filename" : "mscorlib.dll",
"sizeofimage" : "0x470000",
"timestamp" : "0xaf0ada7a",
"il_offset" : "0x00000"
}
,
{
"is_managed" : "false",
"native_address" : "0x16f4ebf3c",
"native_offset" : "0x00000"
}
,
{
"is_managed" : "false",
"native_address" : "0x16f6a1467",
"native_offset" : "0x00000"
}
,
{
"is_managed" : "false",
"native_address" : "0x16f6a2f71",
"native_offset" : "0x00000"
}
,
{
"is_managed" : "false",
"native_address" : "0x16f6c230c",
"native_offset" : "0x00000"
}
,
{
"is_managed" : "false",
"native_address" : "0x16f6c20dd",
"native_offset" : "0x00000"
}
,
{
"is_managed" : "false",
"native_address" : "0x16f73f381",
"native_offset" : "0x00000"
}
,
{
"is_managed" : "false",
"native_address" : "0x16f73f319",
"native_offset" : "0x00000"
}
,
{
"is_managed" : "false",
"native_address" : "0x7ff815f5adf1",
"native_offset" : "0x00000"
}
,
{
"is_managed" : "false",
"native_address" : "0x7ff815f56857",
"native_offset" : "0x00000"
}

]
},
{
"is_managed" : false,
"offset_free_hash" : "0x0",
"offset_rich_hash" : "0x0",
"crashed" : false,
"native_thread_id" : "0x30dd84000",
"thread_info_addr" : "0x7feb95a63a00",
"thread_name" : "Finalizer",
"ctx" : {
"IP" : "0x7ff815f18ac6",
"SP" : "0x30dd83e18",
"BP" : "0x30dd83e60"
},
"unmanaged_frames" : [
{
"is_managed" : "false",
"native_address" : "0x16f56851a",
"native_offset" : "0x00000"
}
,
{
"is_managed" : "false",
"native_address" : "0x16f6c14f0",
"native_offset" : "0x00000"
}
,
{
"is_managed" : "false",
"native_address" : "0x16f6c182a",
"native_offset" : "0x00000"
}
,
{
"is_managed" : "false",
"native_address" : "0x16f6c15e1",
"native_offset" : "0x00000"
}
,
{
"is_managed" : "false",
"native_address" : "0x16f5c5d71",
"native_offset" : "0x00000"
}
,
{
"is_managed" : "false",
"native_address" : "0x7ff815f9325d",
"native_offset" : "0x00000"
}
,
{
"is_managed" : "false",
"native_address" : "0x7febd87e8000",
"native_offset" : "0x00000"
}
,
{
"is_managed" : "false",
"native_address" : "0x16f6c2238",
"native_offset" : "0x00000"
}
,
{
"is_managed" : "false",
"native_address" : "0x16f6c20dd",
"native_offset" : "0x00000"
}
,
{
"is_managed" : "false",
"native_address" : "0x16f73f381",
"native_offset" : "0x00000"
}
,
{
"is_managed" : "false",
"native_address" : "0x16f73f319",
"native_offset" : "0x00000"
}
,
{
"is_managed" : "false",
"native_address" : "0x7ff815f5adf1",
"native_offset" : "0x00000"
}
,
{
"is_managed" : "false",
"native_address" : "0x7ff815f56857",
"native_offset" : "0x00000"
}

]
},
{
"is_managed" : true,
"offset_free_hash" : "0xd742ffd7c",
"offset_rich_hash" : "0xd742fff74",
"crashed" : false,
"native_thread_id" : "0x30f634000",
"thread_info_addr" : "0x7febe33edc00",
"thread_name" : "tid_5bd03",
"ctx" : {
"IP" : "0x7ff815f1b6f6",
"SP" : "0x30f6335d8",
"BP" : "0x30f633670"
},
"managed_frames" : [
{
"is_managed" : "false",
"native_address" : "unregistered"
}
,
{
"is_managed" : "true",
"guid" : "E38A6D3E-E47C-43EB-9B2E-49C63FC0AA48",
"token" : "0x00000",
"native_offset" : "0x0",
"filename" : "mscorlib.dll",
"sizeofimage" : "0x470000",
"timestamp" : "0xaf0ada7a",
"il_offset" : "0x00000"
}
,
{
"is_managed" : "true",
"guid" : "E38A6D3E-E47C-43EB-9B2E-49C63FC0AA48",
"token" : "0x6001f5d",
"native_offset" : "0x0",
"filename" : "mscorlib.dll",
"sizeofimage" : "0x470000",
"timestamp" : "0xaf0ada7a",
"il_offset" : "0x0002f"
}
,
{
"is_managed" : "true",
"guid" : "E38A6D3E-E47C-43EB-9B2E-49C63FC0AA48",
"token" : "0x6001f50",
"native_offset" : "0x0",
"filename" : "mscorlib.dll",
"sizeofimage" : "0x470000",
"timestamp" : "0xaf0ada7a",
"il_offset" : "0x0000e"
}
,
{
"is_managed" : "true",
"guid" : "E38A6D3E-E47C-43EB-9B2E-49C63FC0AA48",
"token" : "0x6001f52",
"native_offset" : "0x0",
"filename" : "mscorlib.dll",
"sizeofimage" : "0x470000",
"timestamp" : "0xaf0ada7a",
"il_offset" : "0x00000"
}
,
{
"is_managed" : "true",
"guid" : "D5F9CBDF-B9F0-4FBF-95C8-63FB10686ED4",
"token" : "0x6003f28",
"native_offset" : "0x0",
"filename" : "unityplastic.dll",
"sizeofimage" : "0x4c0000",
"timestamp" : "0x6228ec27",
"il_offset" : "0x00014"
}
,
{
"is_managed" : "true",
"guid" : "D5F9CBDF-B9F0-4FBF-95C8-63FB10686ED4",
"token" : "0x6003f27",
"native_offset" : "0x0",
"filename" : "unityplastic.dll",
"sizeofimage" : "0x4c0000",
"timestamp" : "0x6228ec27",
"il_offset" : "0x0008a"
}
,
{
"is_managed" : "true",
"guid" : "D5F9CBDF-B9F0-4FBF-95C8-63FB10686ED4",
"token" : "0x6003f2b",
"native_offset" : "0x0",
"filename" : "unityplastic.dll",
"sizeofimage" : "0x4c0000",
"timestamp" : "0x6228ec27",
"il_offset" : "0x00000"
}
,
{
"is_managed" : "true",
"guid" : "E38A6D3E-E47C-43EB-9B2E-49C63FC0AA48",
"token" : "0x6001f7d",
"native_offset" : "0x0",
"filename" : "mscorlib.dll",
"sizeofimage" : "0x470000",
"timestamp" : "0xaf0ada7a",
"il_offset" : "0x00014"
}
,
{
"is_managed" : "true",
"guid" : "E38A6D3E-E47C-43EB-9B2E-49C63FC0AA48",
"token" : "0x6001f25",
"native_offset" : "0x0",
"filename" : "mscorlib.dll",
"sizeofimage" : "0x470000",
"timestamp" : "0xaf0ada7a",
"il_offset" : "0x00071"
}
,
{
"is_managed" : "true",
"guid" : "E38A6D3E-E47C-43EB-9B2E-49C63FC0AA48",
"token" : "0x6001f23",
"native_offset" : "0x0",
"filename" : "mscorlib.dll",
"sizeofimage" : "0x470000",
"timestamp" : "0xaf0ada7a",
"il_offset" : "0x00000"
}
,
{
"is_managed" : "true",
"guid" : "E38A6D3E-E47C-43EB-9B2E-49C63FC0AA48",
"token" : "0x6001f22",
"native_offset" : "0x0",
"filename" : "mscorlib.dll",
"sizeofimage" : "0x470000",
"timestamp" : "0xaf0ada7a",
"il_offset" : "0x0002b"
}
,
{
"is_managed" : "true",
"guid" : "E38A6D3E-E47C-43EB-9B2E-49C63FC0AA48",
"token" : "0x6001f7f",
"native_offset" : "0x0",
"filename" : "mscorlib.dll",
"sizeofimage" : "0x470000",
"timestamp" : "0xaf0ada7a",
"il_offset" : "0x00008"
}
,
{
"is_managed" : "true",
"guid" : "E38A6D3E-E47C-43EB-9B2E-49C63FC0AA48",
"token" : "0x00000",
"native_offset" : "0x0",
"filename" : "mscorlib.dll",
"sizeofimage" : "0x470000",
"timestamp" : "0xaf0ada7a",
"il_offset" : "0x00065"
}

],
"unmanaged_frames" : [
{
"is_managed" : "false",
"native_address" : "0x16f56851a",
"native_offset" : "0x00000"
}
,
{
"is_managed" : "false",
"native_address" : "0x16f6c14f0",
"native_offset" : "0x00000"
}
,
{
"is_managed" : "false",
"native_address" : "0x16f6c182a",
"native_offset" : "0x00000"
}
,
{
"is_managed" : "false",
"native_address" : "0x16f6c15e1",
"native_offset" : "0x00000"
}
,
{
"is_managed" : "false",
"native_address" : "0x16f5c5d71",
"native_offset" : "0x00000"
}
,
{
"is_managed" : "false",
"native_address" : "0x7ff815f9325d",
"native_offset" : "0x00000"
}
,
{
"is_managed" : "false",
"native_address" : "0x1157a8600",
"native_offset" : "0x00000"
}
,
{
"is_managed" : "false",
"native_address" : "0x16f70ff4c",
"native_offset" : "0x00000"
}
,
{
"is_managed" : "false",
"native_address" : "0x16f6cc545",
"native_offset" : "0x00000"
}
,
{
"is_managed" : "false",
"native_address" : "0x16f6cc3a7",
"native_offset" : "0x00000"
}
,
{
"is_managed" : "false",
"native_address" : "0x16f6fcc2c",
"native_offset" : "0x00000"
}
,
{
"is_managed" : "false",
"native_address" : "0x16f666827",
"native_offset" : "0x00000"
}
,
{
"is_managed" : "true",
"guid" : "E38A6D3E-E47C-43EB-9B2E-49C63FC0AA48",
"token" : "0x00000",
"native_offset" : "0x0",
"filename" : "mscorlib.dll",
"sizeofimage" : "0x470000",
"timestamp" : "0xaf0ada7a",
"il_offset" : "0x00000"
}
,
{
"is_managed" : "true",
"guid" : "E38A6D3E-E47C-43EB-9B2E-49C63FC0AA48",
"token" : "0x6001f50",
"native_offset" : "0x0",
"filename" : "mscorlib.dll",
"sizeofimage" : "0x470000",
"timestamp" : "0xaf0ada7a",
"il_offset" : "0x00000"
}
,
{
"is_managed" : "true",
"guid" : "D5F9CBDF-B9F0-4FBF-95C8-63FB10686ED4",
"token" : "0x6003f27",
"native_offset" : "0x0",
"filename" : "unityplastic.dll",
"sizeofimage" : "0x4c0000",
"timestamp" : "0x6228ec27",
"il_offset" : "0x00000"
}
,
{
"is_managed" : "true",
"guid" : "D5F9CBDF-B9F0-4FBF-95C8-63FB10686ED4",
"token" : "0x6003f2b",
"native_offset" : "0x0",
"filename" : "unityplastic.dll",
"sizeofimage" : "0x4c0000",
"timestamp" : "0x6228ec27",
"il_offset" : "0x00000"
}
,
{
"is_managed" : "true",
"guid" : "E38A6D3E-E47C-43EB-9B2E-49C63FC0AA48",
"token" : "0x6001f23",
"native_offset" : "0x0",
"filename" : "mscorlib.dll",
"sizeofimage" : "0x470000",
"timestamp" : "0xaf0ada7a",
"il_offset" : "0x00000"
}
,
{
"is_managed" : "false",
"native_address" : "0x16f4ebf3c",
"native_offset" : "0x00000"
}
,
{
"is_managed" : "false",
"native_address" : "0x16f6a1467",
"native_offset" : "0x00000"
}
,
{
"is_managed" : "false",
"native_address" : "0x16f6a2f71",
"native_offset" : "0x00000"
}
,
{
"is_managed" : "false",
"native_address" : "0x16f6c230c",
"native_offset" : "0x00000"
}
,
{
"is_managed" : "false",
"native_address" : "0x16f6c20dd",
"native_offset" : "0x00000"
}
,
{
"is_managed" : "false",
"native_address" : "0x16f73f381",
"native_offset" : "0x00000"
}
,
{
"is_managed" : "false",
"native_address" : "0x16f73f319",
"native_offset" : "0x00000"
}
,
{
"is_managed" : "false",
"native_address" : "0x7ff815f5adf1",
"native_offset" : "0x00000"
}
,
{
"is_managed" : "false",
"native_address" : "0x7ff815f56857",
"native_offset" : "0x00000"
}

]
}
]
}